docs/source/conf.py
tests/__init__.py
tests/base.py
tests/conftest.py
tests/graph_mock.py
tests/helpers.py
tests/test_beam.py
tests/test_context.py
tests/test_cpu_db.py
tests/test_dependency_monkey.py
tests/test_dm_report.py
tests/test_exceptions.py
tests/test_pipeline_builder.py
tests/test_pipeline_config.py
tests/test_predictor.py
tests/test_product.py
tests/test_report.py
tests/test_resolver.py
tests/test_rules.py
tests/test_solver.py
tests/test_state.py
tests/test_step.py
tests/test_unit.py
tests/boots/__init__.py
tests/boots/test_cve_timestamp.py
tests/boots/test_environment_info.py
tests/boots/test_fully_specified_environment.py
tests/boots/test_labels.py
tests/boots/test_pipfile_hash.py
tests/boots/test_platform.py
tests/boots/test_prescription_release.py
tests/boots/test_python_version.py
tests/boots/test_rhel_version.py
tests/boots/test_solved_software_environment.py
tests/boots/test_solvers_configured.py
tests/boots/test_thoth_s2i.py
tests/boots/test_thoth_s2i_info.py
tests/boots/test_thoth_search.py
tests/boots/test_ubi.py
tests/boots/test_version_check.py
tests/predictors/__init__.py
tests/predictors/test_annealing.py
tests/predictors/test_hill_climbing.py
tests/predictors/test_latest.py
tests/predictors/test_mcts.py
tests/predictors/test_package_combinations.py
tests/predictors/test_random_walk.py
tests/predictors/test_sampling.py
tests/predictors/test_td.py
tests/prescription/__init__.py
tests/prescription/v1/__init__.py
tests/prescription/v1/base.py
tests/prescription/v1/test_add_package_step.py
tests/prescription/v1/test_boot.py
tests/prescription/v1/test_gh_release_notes.py
tests/prescription/v1/test_group.py
tests/prescription/v1/test_prescription.py
tests/prescription/v1/test_pseudonym.py
tests/prescription/v1/test_sieve.py
tests/prescription/v1/test_skip_package_sieve.py
tests/prescription/v1/test_skip_package_step.py
tests/prescription/v1/test_step.py
tests/prescription/v1/test_stride.py
tests/prescription/v1/test_unit.py
thoth_adviser-0.56.3.dist-info/LICENSE
thoth_adviser-0.56.3.dist-info/METADATA
thoth_adviser-0.56.3.dist-info/WHEEL
thoth_adviser-0.56.3.dist-info/entry_points.txt
thoth_adviser-0.56.3.dist-info/top_level.txt
thoth_adviser-0.56.3.dist-info/RECORD
