Metadata-Version: 2.1
Name: thoth-adviser
Version: 0.56.3
Summary: Package and package stack adviser for the Thoth project
Home-page: https://github.com/thoth-station/adviser
Download-URL: https://pypi.org/project/thoth-adviser
Author: Fridolin Pokorny
Author-email: fridolin@redhat.com
License: GPLv3+
License-File: LICENSE
Requires-Dist: attrs
Requires-Dist: click
Requires-Dist: contoml (==0.30)
Requires-Dist: fext (>=0.2.0)
Requires-Dist: matplotlib
Requires-Dist: thoth-python
Requires-Dist: thoth-solver
Requires-Dist: thoth-storages
Requires-Dist: toml
Requires-Dist: pyyaml
Requires-Dist: voluptuous
